gmtool/__init__.py
gmtool/tools.py
gmtool/util.py
gmtools-0.0.6.dist-info/METADATA
gmtools-0.0.6.dist-info/WHEEL
gmtools-0.0.6.dist-info/top_level.txt
gmtools-0.0.6.dist-info/RECORD
