Metadata-Version: 2.1
Name: gmtools
Version: 0.0.6
Summary: gmtool
Home-page: https://github.com/meihaoyidian/tm-pip-tools
Author: GM-TM-QA
Author-email: vida112728@gmail.com
License: MIT
Platform: UNKNOWN
Classifier: License :: OSI Approved :: MIT License
Classifier: Programming Language :: Python
Classifier: Programming Language :: Python :: 3
Requires-Python: >=3.9.0
Requires-Dist: yagmail
Requires-Dist: urllib
Requires-Dist: requests
Requires-Dist: json
